[{"name":"沒能成為魔法使的女孩子","date":"","time":"","carrier":"Original","season":1,"originalName":"魔法使いになれなかった女の子の話。","img":"http://i0.hdslb.com/bfs/new_dyn/961ce5be97887f1521c37be65918ad02512995925.jpg","description":"","staff":""},{"name":"機械臂","date":"","time":"","carrier":"Original","season":1,"originalName":"メカウデ","img":"http://i0.hdslb.com/bfs/new_dyn/1a950cc7c164d0f3a49a5bbd1fd0fe35512995925.jpg","description":"","staff":""},{"name":"負正釣魚","date":"","time":"","carrier":"Original","season":1,"originalName":"ネガポジアングラー","img":"http://i0.hdslb.com/bfs/new_dyn/646282d0d89baa8634ad2bda264e54f0512995925.jpg","description":"","staff":""},{"name":"GOD.app 神明選拔 ","date":"","time":"","carrier":"Original","season":2,"originalName":"カミエラビ","img":"http://i0.hdslb.com/bfs/new_dyn/99180b15419a02f296b0a922bc9eb63a512995925.jpg","description":"","staff":""},{"name":"LoveLive! SuperStar!! ","date":"","time":"","carrier":"Original","season":3,"originalName":"ラブライブ！スーパースター!! 3期","img":"http://i0.hdslb.com/bfs/new_dyn/9577c5681675399c8f1c3b391287ede4512995925.jpg","description":"","staff":""},{"name":"機動戰士高達 復仇的安魂曲","date":"","time":"","carrier":"Original","season":1,"originalName":"機動戦士ガンダム 復讐のレクイエム","img":"http://i0.hdslb.com/bfs/new_dyn/0b109bc3592dd2907893a6c6e7b62279512995925.jpg","description":"","staff":""},{"name":"新 亂馬1/2","date":"","time":"","carrier":"Original","season":1,"originalName":"らんま1/2","img":"http://i0.hdslb.com/bfs/new_dyn/9e906b2860f9f3970ed3af989cd072d4512995925.jpg","description":"","staff":""},{"name":"龍珠 大魔","date":"","time":"","carrier":"Original","season":1,"originalName":"ドラゴンボールDAIMA","img":"http://i0.hdslb.com/bfs/new_dyn/69d37df5b432eec098f52077d308e743512995925.jpg","description":"","staff":""},{"name":"死神 千年血戰篇 Part.3","date":"","time":"","carrier":"Original","season":1,"originalName":"BLEACH 千年血戦篇 -相剋譚-","img":"http://i0.hdslb.com/bfs/new_dyn/432a5323cd9968919c42d9d9936151f9512995925.jpg","description":"","staff":""},{"name":"夏目友人帳 ","date":"","time":"","carrier":"Original","season":7,"originalName":"夏目友人帳 漆","img":"http://i0.hdslb.com/bfs/new_dyn/e33533ed70b54a844d7b6db8b05699b4512995925.jpg","description":"","staff":""},{"name":"新 浪客劍心 ","date":"","time":"","carrier":"Original","season":2,"originalName":"るろうに剣心 -明治剣客浪漫譚- 京都動乱","img":"http://i0.hdslb.com/bfs/new_dyn/37b723d5556534bfae5d5cc09bd8c61d512995925.jpg","description":"","staff":""},{"name":"青之驅魔師 ","date":"","time":"","carrier":"Original","season":4,"originalName":"青の祓魔師 雪ノ果篇&終夜篇","img":"http://i0.hdslb.com/bfs/new_dyn/a11429d8477082dca9299b10854c6dd4512995925.jpg","description":"","staff":""},{"name":"新網球王子 U-17 世界盃 半決賽篇","date":"","time":"","carrier":"Original","season":1,"originalName":"新テニスの王子様 U-17 WORLD CUP SEMIFINAL","img":"http://i0.hdslb.com/bfs/new_dyn/7c1b63d1d4c9c66abea92a9fc25aedce512995925.jpg","description":"","staff":""},{"name":"鴨乃橋論的禁忌推理 ","date":"","time":"","carrier":"Original","season":2,"originalName":"鴨乃橋ロンの禁断推理 2nd Season","img":"http://i0.hdslb.com/bfs/new_dyn/5647287ad67c4a81a19fa6f10a3a3784512995925.jpg","description":"","staff":""},{"name":"七大罪 默示錄的四騎士 ","date":"","time":"","carrier":"Original","season":2,"originalName":"七つの大罪 黙示録の四騎士 ","img":"http://i0.hdslb.com/bfs/new_dyn/02f0c4c603cb692107672f8bc5f4d26e512995925.jpg","description":"","staff":""},{"name":"藍色監獄 ","date":"","time":"","carrier":"Original","season":2,"originalName":"ブルーロック VS. U-20 JAPAN","img":"http://i0.hdslb.com/bfs/new_dyn/80a047ccf724c801ee29c02136c684d4512995925.jpg","description":"","staff":""},{"name":"MF Ghost 極速車魂 ","date":"","time":"","carrier":"Original","season":2,"originalName":"MFゴースト 2nd Season","img":"http://i0.hdslb.com/bfs/new_dyn/18800dc007e9ebea191aecee860f95d9512995925.jpg","description":"","staff":""},{"name":"喂！蜻蜓 ","date":"","time":"","carrier":"Original","season":2,"originalName":"オーイ！とんぼ ","img":"http://i0.hdslb.com/bfs/new_dyn/f6f52187a71ca3668a74990b9ac752cc512995925.jpg","description":"","staff":""},{"name":"放學後少年花子君 ","date":"","time":"","carrier":"Original","season":2,"originalName":"放課後少年花子くん 続編","img":"https://i0.hdslb.com/bfs/new_dyn/02e6719abb88b729d48e6dbea79a12b1512995925.jpg","description":"","staff":""},{"name":"百姓貴族 ","date":"","time":"","carrier":"Original","season":2,"originalName":"百姓貴族 2nd Season","img":"http://i0.hdslb.com/bfs/new_dyn/8e4c2f11a31df46f836fc3be3a0efda3512995925.jpg","description":"","staff":""},{"name":"決鬥大師LOST 追憶之水晶","date":"","time":"","carrier":"Original","season":1,"originalName":"Duel Masters LOST ～追憶の水晶～","img":"http://i0.hdslb.com/bfs/new_dyn/a9b65196cc75bcb6a8879bc553cfea15512995925.jpg","description":"","staff":""},{"name":"伊藤潤二《旋渦》","date":"","time":"","carrier":"Original","season":1,"originalName":"Uzumaki","img":"http://i0.hdslb.com/bfs/new_dyn/e17c0e89f69fbcd99fa5210116ab4064512995925.jpg","description":"","staff":""},{"name":"一兆遊戲","date":"","time":"","carrier":"Original","season":1,"originalName":"トリリオンゲーム","img":"http://i0.hdslb.com/bfs/new_dyn/ad328947dd1b7f9006aae5dd9a97dcdb512995925.jpg","description":"","staff":""},{"name":"凍牌","date":"","time":"","carrier":"Original","season":1,"originalName":"凍牌","img":"https://i0.hdslb.com/bfs/new_dyn/83bb71cb71e7365d12ac7966d3ae07e4512995925.jpg","description":"","staff":""},{"name":"關於地球的運動","date":"","time":"","carrier":"Original","season":1,"originalName":"チ。―地球の運動について―","img":"http://i0.hdslb.com/bfs/new_dyn/5e6aadde7081c57609db3ef291ec265e512995925.jpg","description":"","staff":""},{"name":"青之壬生狼","date":"","time":"","carrier":"Original","season":1,"originalName":"青のミブロ","img":"http://i0.hdslb.com/bfs/new_dyn/99c04ee43b8b2362c1297a2f85027dd9512995925.jpg","description":"","staff":""},{"name":"稗記舞詠 (尋神的旅途)","date":"","time":"","carrier":"Original","season":1,"originalName":"ハイガクラ","img":"http://i0.hdslb.com/bfs/new_dyn/728108c6852768bb1b80652ac5dfeb7b512995925.jpg","description":"","staff":""},{"name":"辰星降臨之國的妮娜","date":"","time":"","carrier":"Original","season":1,"originalName":"星降る王国のニナ","img":"http://i0.hdslb.com/bfs/new_dyn/f247ce178c8388e8f3179afeacb24a77512995925.jpg","description":"","staff":""},{"name":"唯願來世不相識","date":"","time":"","carrier":"Original","season":1,"originalName":"来世は他人がいい","img":"http://i0.hdslb.com/bfs/new_dyn/1279907ffd85a9222a0f00916211d7e9512995925.jpg","description":"","staff":""},{"name":"妻子變成小學生","date":"","time":"","carrier":"Original","season":1,"originalName":"妻、小学生になる。","img":"http://i0.hdslb.com/bfs/new_dyn/b5d2496e3392caad0fddf7eea7b8db5b512995925.jpg","description":"","staff":""},{"name":"真的要結婚嗎","date":"","time":"","carrier":"Original","season":1,"originalName":"結婚するって、本当ですか","img":"http://i0.hdslb.com/bfs/new_dyn/03fe9f8eee618ff211bff03a0312106d512995925.jpg","description":"","staff":""},{"name":"村井之戀","date":"","time":"","carrier":"Original","season":1,"originalName":"村井の恋","img":"http://i0.hdslb.com/bfs/new_dyn/c5cc717bb820908013b858dbef587d44512995925.jpg","description":"","staff":""},{"name":"去聯誼卻發現沒有女生","date":"","time":"","carrier":"Original","season":1,"originalName":"合コンに行ったら女がいなかった話","img":"http://i0.hdslb.com/bfs/new_dyn/9593d7c9de0b242f4f5832e9e1ab7906512995925.jpg","description":"","staff":""},{"name":"青春之箱 (藍箱)","date":"","time":"","carrier":"Original","season":1,"originalName":"アオのハコ","img":"http://i0.hdslb.com/bfs/new_dyn/bfbd754eb594895e62fe825058681d06512995925.jpg","description":"","staff":""},{"name":"緣結甘神家","date":"","time":"","carrier":"Original","season":1,"originalName":"甘神さんちの縁結び","img":"https://i0.hdslb.com/bfs/new_dyn/464d91ebef0e07f7636c20747e77eb96512995925.jpg","description":"","staff":""},{"name":"暗殺女僕冥土小姐","date":"","time":"","carrier":"Original","season":1,"originalName":"君は冥土様。","img":"http://i0.hdslb.com/bfs/new_dyn/391d4b565397016d1905fe5c5e35b30c512995925.jpg","description":"","staff":""},{"name":"柔光魔女股份有限公司","date":"","time":"","carrier":"Original","season":1,"originalName":"株式会社マジルミエ","img":"http://i0.hdslb.com/bfs/new_dyn/7eeb624a6ef3df969f163619b2fa6749512995925.jpg","description":"","staff":""},{"name":"Acro Trip","date":"","time":"","carrier":"Original","season":1,"originalName":"アクロトリップ","img":"http://i0.hdslb.com/bfs/new_dyn/3804b02657cd62bd6e8c7a0583a5c12c512995925.jpg","description":"","staff":""},{"name":"超自然武裝當噠當 (膽大黨)","date":"","time":"","carrier":"Original","season":1,"originalName":"ダンダダン","img":"http://i0.hdslb.com/bfs/new_dyn/80900410228dcd8aac166a0418344d92512995925.jpg","description":"","staff":""},{"name":"妖怪學校的新人教師","date":"","time":"","carrier":"Original","season":1,"originalName":"妖怪学校の先生はじめました！","img":"http://i0.hdslb.com/bfs/new_dyn/f327b8d9c38a9fd818be9ec1068b2d93512995925.jpg","description":"","staff":""},{"name":"科學×冒險求生","date":"","time":"","carrier":"Original","season":1,"originalName":"科学×冒険サバイバル","img":"http://i0.hdslb.com/bfs/new_dyn/2646242f8d8455bec0911854632de0e4512995925.jpg","description":"","staff":""},{"name":"蘑菇狗","date":"","time":"","carrier":"Original","season":1,"originalName":"きのこいぬ ","img":"http://i0.hdslb.com/bfs/new_dyn/6f222133f198b7314fc0677fa0330a73512995925.jpg","description":"","staff":""},{"name":"殿下與狗","date":"","time":"","carrier":"Original","season":1,"originalName":"殿と犬","img":"http://i0.hdslb.com/bfs/new_dyn/5bba6a19a3ceeaba369be37a114bdc4b512995925.jpg","description":"","staff":""},{"name":"轉生成貓的大叔","date":"","time":"","carrier":"Original","season":1,"originalName":"ねこに転生したおじさん","img":"http://i0.hdslb.com/bfs/new_dyn/264f940c19e2939964456f69f858112a512995925.jpg","description":"","staff":""},{"name":"可愛史萊姆噗尼露","date":"","time":"","carrier":"Original","season":1,"originalName":"ぷにるはかわいいスライム","img":"http://i0.hdslb.com/bfs/new_dyn/eb253c9ba32b4e14d142e129ce7f2eb7512995925.jpg","description":"","staff":""},{"name":"在地下城尋求邂逅是否搞錯了什麼","date":"","time":"","carrier":"Original","season":5,"originalName":"ダンジョンに出会いを求めるのは間違っているだろうか ","img":"http://i0.hdslb.com/bfs/new_dyn/1455db1f38c64ff67636855d8f97067b512995925.jpg","description":"","staff":""},{"name":"Re:從零開始的異世界生活 ","date":"","time":"","carrier":"Original","season":3,"originalName":"Re:ゼロから始める異世界生活 3rd season","img":"http://i0.hdslb.com/bfs/new_dyn/25db51d0aeb240d2c5e6ff0fc9c24f6a512995925.jpg","description":"","staff":""},{"name":"平凡職業造就世界最強 ","date":"","time":"","carrier":"Original","season":3,"originalName":"ありふれた職業で世界最強 3rd season","img":"http://i0.hdslb.com/bfs/new_dyn/6b88ca90ff198cbcba966b13fb8381c0512995925.jpg","description":"","staff":""},{"name":"精靈幻想記 ","date":"","time":"","carrier":"Original","season":2,"originalName":"精霊幻想記 ","img":"http://i0.hdslb.com/bfs/new_dyn/0a7805c07dc72d988d88dea24636b273512995925.jpg","description":"","staff":""},{"name":"轉生貴族靠著鑑定技能一飛沖天","date":"","time":"","carrier":"Original","season":2,"originalName":"転生貴族、鑑定スキルで成り上がる ","img":"http://i0.hdslb.com/bfs/new_dyn/bd0febd06c1de155d920d27bca210c30512995925.jpg","description":"","staff":""},{"name":"香格里拉邊境 ","date":"","time":"","carrier":"Original","season":2,"originalName":"シャングリラ・フロンティア 2nd Season","img":"http://i0.hdslb.com/bfs/new_dyn/54a7511b7229e23b2e7696026a1265ee512995925.jpg","description":"","staff":""},{"name":"Gun Gale Online ","date":"","time":"","carrier":"Original","season":2,"originalName":"ガンゲイル・オンライン ","img":"http://i0.hdslb.com/bfs/new_dyn/6c23e7156ffa7dc56c59315179aa0a80512995925.jpg","description":"","staff":""},{"name":"重來吧魔王大人R","date":"","time":"","carrier":"Original","season":1,"originalName":"魔王様、リトライ！R","img":"http://i0.hdslb.com/bfs/new_dyn/8e019b932751e8266e52882a8fc16cc6512995925.jpg","description":"","staff":""},{"name":"魔王2099","date":"","time":"","carrier":"Original","season":1,"originalName":"魔王2099","img":"http://i0.hdslb.com/bfs/new_dyn/56394fe284a78a22b664bc21b6cc6fdf512995925.jpg","description":"","staff":""},{"name":"最狂輔助職業話術士世界最強戰團聽我號令","date":"","time":"","carrier":"Original","season":1,"originalName":"最凶の支援職【話術士】である俺は世界最強クランを従える","img":"http://i0.hdslb.com/bfs/new_dyn/8efd87aa65b85c4472d89608a1b2fffd512995925.jpg","description":"","staff":""},{"name":"嘆息的亡靈好想隱退","date":"","time":"","carrier":"Original","season":1,"originalName":"嘆きの亡霊は引退したい","img":"http://i0.hdslb.com/bfs/new_dyn/c7260b15ebc1d7c78ff5244dcf63da43512995925.jpg","description":"","staff":""},{"name":"被隊伍驅逐的治癒師其實是最強的","date":"","time":"","carrier":"Original","season":1,"originalName":"パーティーから追放されたその治癒師、実は最強につき","img":"http://i0.hdslb.com/bfs/new_dyn/04d7c72bedddef38ce711b15341e7b71512995925.jpg","description":"","staff":""},{"name":"再見龍生 你好人生","date":"","time":"","carrier":"Original","season":1,"originalName":"さようなら竜生、こんにちは人生","img":"http://i0.hdslb.com/bfs/new_dyn/a098e09b021f1f69b1f8c39b82240257512995925.jpg","description":"","staff":""},{"name":"獨自一人的異世界攻略","date":"","time":"","carrier":"Original","season":1,"originalName":"ひとりぼっちの異世界攻略","img":"http://i0.hdslb.com/bfs/new_dyn/7e7a8d27b64152559502ea846d71057f512995925.jpg","description":"","staff":""},{"name":"成為名垂青史的惡役千金吧","date":"","time":"","carrier":"Original","season":1,"originalName":"歴史に残る悪女になるぞ","img":"http://i0.hdslb.com/bfs/new_dyn/2973c66cd2c4a5266765e007c2b64619512995925.jpg","description":"","staff":""},{"name":"重生大小姐正在攻略龍帝殿下","date":"","time":"","carrier":"Original","season":1,"originalName":"やり直し令嬢は竜帝陛下を攻略中","img":"http://i0.hdslb.com/bfs/new_dyn/a5a816b3e20cb456ae8eac9d21651b47512995925.jpg","description":"","staff":""},{"name":"偶像大師 閃耀色彩 ","date":"","time":"","carrier":"Original","season":2,"originalName":"THE iDOLM@STER SHINYCOLORS 2nd season","img":"http://i0.hdslb.com/bfs/new_dyn/0e07aed0d895615f545e120a4cd5bc25512995925.jpg","description":"","staff":""},{"name":"常軌脫離Creative","date":"","time":"","carrier":"Original","season":1,"originalName":"ハミダシクリエイティブ","img":"http://i0.hdslb.com/bfs/new_dyn/1e36f7663ddb3afa285d3b9807229003512995925.jpg","description":"","staff":""},{"name":"購物熊貓","date":"","time":"","carrier":"Original","season":1,"originalName":"お買いものパンダ！","img":"http://i0.hdslb.com/bfs/new_dyn/eccb8c8436e99f4affefb64b57be0978512995925.jpg","description":"","staff":""},{"name":"澀谷♥八公 ","date":"","time":"","carrier":"Original","season":2,"originalName":"SHIBUYA♥HACHI 第2クール","img":"http://i0.hdslb.com/bfs/new_dyn/1b8d4303e5c17f0243a78ba620d4bee4512995925.jpg","description":"","staff":""},{"name":"香蕉喵 ","date":"","time":"","carrier":"Original","season":3,"originalName":"ばなにゃ あらうんど ざ わーるど","img":"http://i0.hdslb.com/bfs/new_dyn/52ffdfc48762759f275518a590bbafae512995925.jpg","description":"","staff":""},{"name":"噗尼輪輪 ","date":"","time":"","carrier":"Original","season":2,"originalName":"ぷにるんず ぷに２","img":"http://i0.hdslb.com/bfs/new_dyn/d09e8350c5ede5ce0a04698a0d01a390512995925.jpg","description":"","staff":""},{"name":"Kumarba ","date":"","time":"","carrier":"Original","season":2,"originalName":"クマーバ シーズン2","img":"http://i0.hdslb.com/bfs/new_dyn/27f9369b767daabe35653c96e701e94b512995925.jpg","description":"","staff":""}]